z85base91/__init__.py
z85base91/b91.py
z85base91/bench.py
z85base91/libbase91-aarch64.so
z85base91/libbase91-i386.so
z85base91/libbase91-x86_64.so
z85base91/libz85b-aarch64.so
z85base91/libz85b-i386.so
z85base91/libz85b-x86_64.so
z85base91/libz85p-aarch64.so
z85base91/libz85p-i386.so
z85base91/libz85p-x86_64.so
z85base91/version.py
z85base91/z85b.py
z85base91/z85p.py
z85base91-0.0.5.dist-info/LICENSE
z85base91-0.0.5.dist-info/METADATA
z85base91-0.0.5.dist-info/WHEEL
z85base91-0.0.5.dist-info/top_level.txt
z85base91-0.0.5.dist-info/RECORD
